Project-Engine/Shaders.py
Project-Engine/__init__.py
Project-Engine/classes.py
Project-Engine/main.py
ProjectEngine/Shaders.py
ProjectEngine/Textures.py
ProjectEngine/__init__.py
ProjectEngine/classes.py
ProjectEngine/main.py
ProjectEngine-0.2.3.dist-info/METADATA
ProjectEngine-0.2.3.dist-info/WHEEL
ProjectEngine-0.2.3.dist-info/top_level.txt
ProjectEngine-0.2.3.dist-info/RECORD
