Metadata-Version: 2.1
Name: ProjectEngine
Version: 0.2.3
Summary: Basic PyOpenGl project
Author: Oliver Wilkinson
Author-email: otwilkinsonuk@icloud.com
Requires-Dist: pygame
Requires-Dist: PyOpenGl
Requires-Dist: objloader
